odoo/addons/stock_packaging_calculator_packaging_type/README.rst
odoo/addons/stock_packaging_calculator_packaging_type/__init__.py
odoo/addons/stock_packaging_calculator_packaging_type/__manifest__.py
odoo/addons/stock_packaging_calculator_packaging_type/i18n/it.po
odoo/addons/stock_packaging_calculator_packaging_type/i18n/stock_packaging_calculator_packaging_type.pot
odoo/addons/stock_packaging_calculator_packaging_type/models/__init__.py
odoo/addons/stock_packaging_calculator_packaging_type/models/product.py
odoo/addons/stock_packaging_calculator_packaging_type/models/product_qty_by_packaging_mixin.py
odoo/addons/stock_packaging_calculator_packaging_type/readme/CONTRIBUTORS.rst
odoo/addons/stock_packaging_calculator_packaging_type/readme/CREDITS.rst
odoo/addons/stock_packaging_calculator_packaging_type/readme/DESCRIPTION.rst
odoo/addons/stock_packaging_calculator_packaging_type/static/description/icon.png
odoo/addons/stock_packaging_calculator_packaging_type/static/description/index.html
odoo/addons/stock_packaging_calculator_packaging_type/tests/__init__.py
odoo/addons/stock_packaging_calculator_packaging_type/tests/test_packaging_by_qty.py
odoo14_addon_stock_packaging_calculator_packaging_type-14.0.1.0.1.dev6.dist-info/METADATA
odoo14_addon_stock_packaging_calculator_packaging_type-14.0.1.0.1.dev6.dist-info/WHEEL
odoo14_addon_stock_packaging_calculator_packaging_type-14.0.1.0.1.dev6.dist-info/top_level.txt
odoo14_addon_stock_packaging_calculator_packaging_type-14.0.1.0.1.dev6.dist-info/RECORD
