Metadata-Version: 2.1
Name: odoo14-addon-stock-packaging-calculator-packaging-type
Version: 14.0.1.0.1.dev6
Summary: Glue module for packaging type
Home-page: https://github.com/OCA/stock-logistics-warehouse
Author: Camptocamp, Odoo Community Association (OCA)
Author-email: support@odoo-community.org
License: LGPL-3
Platform: UNKNOWN
Classifier: Programming Language :: Python
Classifier: Framework :: Odoo
Classifier: Framework :: Odoo :: 14.0
Classifier: License :: OSI Approved :: GNU Lesser General Public License v3 (LGPLv3)
Classifier: Development Status :: 3 - Alpha
Requires-Python: >=3.6
Requires-Dist: odoo14-addon-product-packaging-type
Requires-Dist: odoo14-addon-stock-packaging-calculator
Requires-Dist: odoo <14.1dev,>=14.0a
